helpers/__init__.py
srswti_cython_windows/api.cp311-win_amd64.pyd
srswti_cython_windows/home.cp311-win_amd64.pyd
srswti_cython_windows/llm.cp311-win_amd64.pyd
srswti_cython_windows/main.cp311-win_amd64.pyd
srswti_cython_windows/models.cp311-win_amd64.pyd
srswti_cython_windows/signup.cp311-win_amd64.pyd
srswti_cython_windows/speech.cp311-win_amd64.pyd
srswti_cython_windows/stt_socket.cp311-win_amd64.pyd
srswti_cython_windows/utils.cp311-win_amd64.pyd
srswti_cython_windows/helpers/chat_history_manager.cp311-win_amd64.pyd
srswti_cython_windows/helpers/node_manager.cp311-win_amd64.pyd
srswti_cython_windows/helpers/profiler.cp311-win_amd64.pyd
srswti_cython_windows/helpers/quick_one.cp311-win_amd64.pyd
srswti_cython_windows/helpers/redis_server.cp311-win_amd64.pyd
srswti_cython_windows/helpers/response_gen_v2.cp311-win_amd64.pyd
srswti_cython_windows/helpers/shared.cp311-win_amd64.pyd
srswti_cython_windows/helpers/stt.cp311-win_amd64.pyd
srswti_cython_windows/helpers/tts.cp311-win_amd64.pyd
srswti_cython_windows/helpers/tts_fastapi.cp311-win_amd64.pyd
srswti_cython_windows-2.0.2.dist-info/METADATA
srswti_cython_windows-2.0.2.dist-info/WHEEL
srswti_cython_windows-2.0.2.dist-info/top_level.txt
srswti_cython_windows-2.0.2.dist-info/RECORD
