Metadata-Version: 2.1
Name: srswti-cython-windows
Version: 2.0.2
Summary: A Cythonized package for srswti
Author: SRSWTI Inc.
Author-email: team@srswti.com
License: MIT
Classifier: Programming Language :: Python :: 3
Classifier: Operating System :: OS Independent
Requires-Python: >=3.8
Requires-Dist: anthropic
Requires-Dist: cerebras-cloud-sdk
Requires-Dist: fastapi
Requires-Dist: gcloud
Requires-Dist: google-ai-generativelanguage
Requires-Dist: google-api-core
Requires-Dist: google-api-python-client
Requires-Dist: google-auth
Requires-Dist: google-auth-httplib2
Requires-Dist: google-cloud-speech
Requires-Dist: google-cloud-texttospeech
Requires-Dist: google-genai
Requires-Dist: google-generativeai
Requires-Dist: googleapis-common-protos
Requires-Dist: grpcio
Requires-Dist: httpx
Requires-Dist: jiter
Requires-Dist: lxml
Requires-Dist: nltk
Requires-Dist: oauth2client
Requires-Dist: openai
Requires-Dist: packaging
Requires-Dist: pillow
Requires-Dist: postgrest
Requires-Dist: PyAudio
Requires-Dist: pydantic
Requires-Dist: pydantic-core
Requires-Dist: pydub
Requires-Dist: pyinstaller
Requires-Dist: python-dotenv
Requires-Dist: redis
Requires-Dist: regex
Requires-Dist: requests
Requires-Dist: starlette
Requires-Dist: supabase
Requires-Dist: tqdm
Requires-Dist: uvicorn
Requires-Dist: websockets
